format_pipfile/__init__.py
format_pipfile/__main__.py
format_pipfile/cli.py
format_pipfile-0.0.6.dist-info/AUTHORS
format_pipfile-0.0.6.dist-info/LICENSE
format_pipfile-0.0.6.dist-info/METADATA
format_pipfile-0.0.6.dist-info/WHEEL
format_pipfile-0.0.6.dist-info/entry_points.txt
format_pipfile-0.0.6.dist-info/pbr.json
format_pipfile-0.0.6.dist-info/top_level.txt
format_pipfile-0.0.6.dist-info/RECORD
